{
  "hash": "f1401a56",
  "configHash": "edbce3b3",
  "lockfileHash": "0a178a96",
  "browserHash": "1a32a57d",
  "optimized": {
    "buffer": {
      "src": "../../../../../node_modules/buffer/index.js",
      "file": "buffer.js",
      "fileHash": "a70d0395",
      "needsInterop": true
    },
    "pinia-plugin-persistedstate": {
      "src": "../../../../../node_modules/pinia-plugin-persistedstate/dist/index.js",
      "file": "pinia-plugin-persistedstate.js",
      "fileHash": "b69256ba",
      "needsInterop": false
    },
    "process": {
      "src": "../../../../../node_modules/process/browser.js",
      "file": "process.js",
      "fileHash": "04d9e99d",
      "needsInterop": true
    },
    "ethers": {
      "src": "../../../../../node_modules/ethers/lib.esm/index.js",
      "file": "ethers.js",
      "fileHash": "2589c8ff",
      "needsInterop": false
    }
  },
  "chunks": {
    "chunk-ZS7NZCD4": {
      "file": "chunk-ZS7NZCD4.js"
    }
  }
}